kenkenpa/__init__.py
kenkenpa/builder.py
kenkenpa/common.py
kenkenpa/edges.py
kenkenpa/models/__init__.py
kenkenpa/models/conditions.py
kenkenpa/models/configurable_conditional_edge.py
kenkenpa/models/configurable_conditional_entry_point.py
kenkenpa/models/edge.py
kenkenpa/models/node.py
kenkenpa/models/stategraph.py
kenkenpa/param.py
kenkenpa/state.py
kenkenpa-0.2.16.dist-info/LICENSE
kenkenpa-0.2.16.dist-info/METADATA
kenkenpa-0.2.16.dist-info/WHEEL
kenkenpa-0.2.16.dist-info/RECORD
