Metadata-Version: 2.3
Name: kenkenpa
Version: 0.2.16
Summary: Generate a StateGraph of LangGraph that can be compiled from structured data.
License: MIT
Author: ONIHEI0910
Author-email: onihei0910_dev@delve-siphon.net
Requires-Python: >= 3.10,<4.0.0
Classifier: License :: OSI Approved :: MIT License
Classifier: Programming Language :: Python :: 3
Classifier: Programming Language :: Python :: 3.10
Classifier: Programming Language :: Python :: 3.11
Classifier: Programming Language :: Python :: 3.12
Classifier: Programming Language :: Python :: 3.13
Requires-Dist: langchain-core (>=0.3.0,<2.0.0)
Requires-Dist: langgraph (>=0.2.2,<2.0.0)
Requires-Dist: pydantic (>=2.9.2,<3.0.0)
